crystal_renderer/__init__.py
crystal_renderer/conversion.py
crystal_renderer/data.py
crystal_renderer/info_panel.py
crystal_renderer/projection.py
crystal_renderer/py.typed
crystal_renderer/rendering.py
crystal_renderer/visualization.py
crystal_renderer/formats/__init__.py
crystal_renderer/formats/gemcad.py
crystal_renderer/formats/gltf.py
crystal_renderer/formats/obj.py
crystal_renderer/formats/stl.py
gemmology_crystal_renderer-1.0.1.dist-info/licenses/LICENSE
gemmology_crystal_renderer-1.0.1.dist-info/METADATA
gemmology_crystal_renderer-1.0.1.dist-info/WHEEL
gemmology_crystal_renderer-1.0.1.dist-info/top_level.txt
gemmology_crystal_renderer-1.0.1.dist-info/RECORD
