Metadata-Version: 2.4
Name: gemmology-crystal-renderer
Version: 1.0.1
Summary: SVG and 3D visualization for crystal geometries
Author-email: Fabian Schuh <fabian@gemmology.dev>
Maintainer-email: Fabian Schuh <fabian@gemmology.dev>
License: MIT
Project-URL: Homepage, https://crystal-renderer.gemmology.dev
Project-URL: Documentation, https://crystal-renderer.gemmology.dev/docs
Project-URL: Repository, https://github.com/gemmology-dev/crystal-renderer
Project-URL: Issues, https://github.com/gemmology-dev/crystal-renderer/issues
Project-URL: Changelog, https://github.com/gemmology-dev/crystal-renderer/blob/main/CHANGELOG.md
Keywords: crystallography,mineralogy,gemmology,visualization,svg,3d,stl,gltf,rendering
Classifier: Development Status :: 5 - Production/Stable
Classifier: Intended Audience :: Science/Research
Classifier: Intended Audience :: Education
Classifier: License :: OSI Approved :: MIT License
Classifier: Operating System :: OS Independent
Classifier: Programming Language :: Python :: 3
Classifier: Programming Language :: Python :: 3.10
Classifier: Programming Language :: Python :: 3.11
Classifier: Programming Language :: Python :: 3.12
Classifier: Programming Language :: Python :: 3.13
Classifier: Topic :: Scientific/Engineering
Classifier: Topic :: Scientific/Engineering :: Chemistry
Classifier: Topic :: Scientific/Engineering :: Visualization
Classifier: Typing :: Typed
Requires-Python: >=3.10
License-File: LICENSE
Requires-Dist: gemmology-cdl-parser>=1.0.0
Requires-Dist: gemmology-crystal-geometry>=1.0.0
Requires-Dist: numpy>=1.20.0
Requires-Dist: matplotlib>=3.5.0
Provides-Extra: dev
Requires-Dist: pytest>=7.0; extra == "dev"
Requires-Dist: pytest-cov>=4.0; extra == "dev"
Requires-Dist: ruff>=0.1.0; extra == "dev"
Requires-Dist: mypy>=1.0; extra == "dev"
Provides-Extra: raster
Requires-Dist: cairosvg>=2.5.0; extra == "raster"
Requires-Dist: Pillow>=9.0.0; extra == "raster"
Provides-Extra: all
Requires-Dist: cairosvg>=2.5.0; extra == "all"
Requires-Dist: Pillow>=9.0.0; extra == "all"
Requires-Dist: ase>=3.22.0; extra == "all"
Provides-Extra: docs
Requires-Dist: mkdocs>=1.5; extra == "docs"
Requires-Dist: mkdocs-material>=9.0; extra == "docs"
Requires-Dist: mkdocstrings[python]>=0.24; extra == "docs"
Dynamic: license-file
